GangaCK/AppUtils.py
GangaCK/ColorPrimer.py
GangaCK/Commands.py
GangaCK/ConfigUtils.py
GangaCK/Decorators.py
GangaCK/IOUtils.py
GangaCK/JobShell.py
GangaCK/JobUtils.py
GangaCK/Magics.py
GangaCK/TaskShell.py
GangaCK/TaskUtils.py
GangaCK/Utils.py
GangaCK/__init__.py
GangaCK/__patcher__.py
GangaCK/Jobtree/BaseJobtreeReader.py
GangaCK/Jobtree/Index.py
GangaCK/Jobtree/JTDecorators.py
GangaCK/Jobtree/OfflineJobtreeReader.py
GangaCK/Jobtree/OnlineJTWriter.py
GangaCK/Jobtree/OnlineJobtreeReader.py
GangaCK/Jobtree/__init__.py
GangaCK/OfflineGPI/DictTree.py
GangaCK/OfflineGPI/OfflineJob.py
GangaCK/OfflineGPI/__init__.py
GangaCK/OfflineGPI/config.py
GangaCK-1.0.0.dist-info/LICENSE.txt
GangaCK-1.0.0.dist-info/METADATA
GangaCK-1.0.0.dist-info/RECORD
GangaCK-1.0.0.dist-info/WHEEL
GangaCK-1.0.0.dist-info/pbr.json
GangaCK-1.0.0.dist-info/top_level.txt
