Metadata-Version: 2.1
Name: GangaCK
Version: 1.0.0
Summary: Improving Ganga for better productivity.
Home-page: https://gitlab.com/ckhurewa/GangaCK
Author: Chitsanu Khurewathanakul
Author-email: chitsanu.khurewathanakul@epfl.ch
License: GNU GPLv3
Platform: unix
Classifier: Development Status :: 4 - Beta
Classifier: Environment :: Console
Classifier: Intended Audience :: Developers
Classifier: Intended Audience :: Information Technology
Classifier: Operating System :: OS Independent
Classifier: Programming Language :: Python :: 2.7
Classifier: Topic :: Utilities
Requires-Python: ~=2.7
Requires-Dist: PythonCK (>=1.0.0)
